{"status":"succeeded","createdDateTime":"2024-08-14T16:23:43Z","lastUpdatedDateTime":"2024-08-14T16:23:45Z","analyzeResult":{"apiVersion":"2024-02-29-preview","modelId":"prebuilt-layout","stringIndexType":"textElements","content":"36\nCHANEL\nEL fumadre de ens época es del mas talgenie que at hi- conocido B haha de que monne una pri- ferencla dichlada por el Carol in prothe evidence de que nie dife- write ha sido creado para serslicer\nLa peine más melindresa ne tradri was mandlo que sesdime were la fraganela de aroma y de genie ivalala por el Cameli - La fe y mura de los tebaore Tur- cos y Americanos, forclados con Haberactie det Conel & propor; cienune el gote min completo del cigarrillo.\nEsta edad moderna sabe escoger lo mejor- por eso fuma cigarrillos Camel\nBHW\n50378 1060","pages":[{"pageNumber":1,"angle":-0.30469998717308044,"width":754,"height":1000,"unit":"pixel","words":[{"content":"36","polygon":[237,136,267,136,268,157,237,158],"confidence":0.993,"span":{"offset":0,"length":2}},{"content":"CHANEL","polygon":[498,454,548,456,548,468,498,466],"confidence":0.473,"span":{"offset":3,"length":6}},{"content":"EL","polygon":[367,474,376,474,376,484,367,484],"confidence":0.53,"span":{"offset":10,"length":2}},{"content":"fumadre","polygon":[378,474,402,474,402,484,378,484],"confidence":0.118,"span":{"offset":13,"length":7}},{"content":"de","polygon":[404,474,411,474,411,484,404,484],"confidence":0.665,"span":{"offset":21,"length":2}},{"content":"ens","polygon":[413,474,424,475,424,483,413,484],"confidence":0.161,"span":{"offset":24,"length":3}},{"content":"época","polygon":[427,475,443,475,443,483,427,483],"confidence":0.062,"span":{"offset":28,"length":5}},{"content":"es","polygon":[445,475,450,475,450,483,445,483],"confidence":0.187,"span":{"offset":34,"length":2}},{"content":"del","polygon":[452,475,461,475,461,483,452,483],"confidence":0.14,"span":{"offset":37,"length":3}},{"content":"mas","polygon":[367,483,379,483,379,491,367,491],"confidence":0.76,"span":{"offset":41,"length":3}},{"content":"talgenie","polygon":[381,483,403,483,403,491,381,491],"confidence":0.213,"span":{"offset":45,"length":8}},{"content":"que","polygon":[405,483,416,483,416,491,405,491],"confidence":0.485,"span":{"offset":54,"length":3}},{"content":"at","polygon":[418,483,423,483,423,491,418,491],"confidence":0.112,"span":{"offset":58,"length":2}},{"content":"hi-","polygon":[425,483,433,482,433,491,424,491],"confidence":0.425,"span":{"offset":61,"length":3}},{"content":"conocido","polygon":[435,482,461,481,461,490,434,491],"confidence":0.226,"span":{"offset":65,"length":8}},{"content":"B","polygon":[367,498,372,498,372,507,367,507],"confidence":0.304,"span":{"offset":74,"length":1}},{"content":"haha","polygon":[375,498,392,498,392,507,375,507],"confidence":0.218,"span":{"offset":76,"length":4}},{"content":"de","polygon":[394,498,400,498,400,507,394,507],"confidence":0.788,"span":{"offset":81,"length":2}},{"content":"que","polygon":[401,498,412,498,412,507,401,507],"confidence":0.355,"span":{"offset":84,"length":3}},{"content":"monne","polygon":[414,498,435,498,435,506,414,507],"confidence":0.535,"span":{"offset":88,"length":5}},{"content":"una","polygon":[436,498,446,498,446,506,436,506],"confidence":0.135,"span":{"offset":94,"length":3}},{"content":"pri-","polygon":[448,498,461,499,461,506,448,506],"confidence":0.441,"span":{"offset":98,"length":4}},{"content":"ferencla","polygon":[368,505,389,505,389,513,368,513],"confidence":0.628,"span":{"offset":103,"length":8}},{"content":"dichlada","polygon":[391,505,413,504,413,513,391,513],"confidence":0.418,"span":{"offset":112,"length":8}},{"content":"por","polygon":[416,504,425,504,425,513,416,513],"confidence":0.72,"span":{"offset":121,"length":3}},{"content":"el","polygon":[427,504,433,504,433,513,427,513],"confidence":0.279,"span":{"offset":125,"length":2}},{"content":"Carol","polygon":[435,504,452,504,452,513,435,513],"confidence":0.079,"span":{"offset":128,"length":5}},{"content":"in","polygon":[453,504,462,505,462,513,453,513],"confidence":0.02,"span":{"offset":134,"length":2}},{"content":"prothe","polygon":[367,513,386,512,386,520,367,521],"confidence":0.358,"span":{"offset":137,"length":6}},{"content":"evidence","polygon":[388,512,411,512,411,520,388,520],"confidence":0.059,"span":{"offset":144,"length":8}},{"content":"de","polygon":[413,512,420,512,420,520,413,520],"confidence":0.773,"span":{"offset":153,"length":2}},{"content":"que","polygon":[422,512,432,512,432,520,422,520],"confidence":0.836,"span":{"offset":156,"length":3}},{"content":"nie","polygon":[435,512,445,512,445,520,435,520],"confidence":0.043,"span":{"offset":160,"length":3}},{"content":"dife-","polygon":[446,512,460,512,460,520,446,520],"confidence":0.069,"span":{"offset":164,"length":5}},{"content":"write","polygon":[367,518,380,518,380,527,367,527],"confidence":0.528,"span":{"offset":170,"length":5}},{"content":"ha","polygon":[381,518,388,518,387,527,381,527],"confidence":0.419,"span":{"offset":176,"length":2}},{"content":"sido","polygon":[389,518,401,518,401,527,389,527],"confidence":0.523,"span":{"offset":179,"length":4}},{"content":"creado","polygon":[402,518,421,518,421,527,402,527],"confidence":0.586,"span":{"offset":184,"length":6}},{"content":"para","polygon":[422,518,434,518,434,526,422,527],"confidence":0.527,"span":{"offset":191,"length":4}},{"content":"serslicer","polygon":[436,518,462,518,462,526,435,526],"confidence":0.278,"span":{"offset":196,"length":9}},{"content":"La","polygon":[368,536,376,535,376,543,368,544],"confidence":0.19,"span":{"offset":206,"length":2}},{"content":"peine","polygon":[378,535,401,534,401,542,378,543],"confidence":0.133,"span":{"offset":209,"length":5}},{"content":"más","polygon":[404,534,415,534,415,542,404,542],"confidence":0.294,"span":{"offset":215,"length":3}},{"content":"melindresa","polygon":[418,534,450,534,450,542,418,542],"confidence":0.3,"span":{"offset":219,"length":10}},{"content":"ne","polygon":[452,534,461,534,461,542,452,542],"confidence":0.112,"span":{"offset":230,"length":2}},{"content":"tradri","polygon":[368,540,386,541,385,549,367,549],"confidence":0.375,"span":{"offset":233,"length":6}},{"content":"was","polygon":[388,541,399,541,398,549,388,549],"confidence":0.15,"span":{"offset":240,"length":3}},{"content":"mandlo","polygon":[401,541,423,541,423,549,401,549],"confidence":0.124,"span":{"offset":244,"length":6}},{"content":"que","polygon":[426,541,436,541,435,549,425,549],"confidence":0.585,"span":{"offset":251,"length":3}},{"content":"sesdime","polygon":[438,541,461,541,460,549,438,549],"confidence":0.413,"span":{"offset":255,"length":7}},{"content":"were","polygon":[368,547,380,547,380,556,368,557],"confidence":0.127,"span":{"offset":263,"length":4}},{"content":"la","polygon":[383,547,388,547,388,556,383,556],"confidence":0.726,"span":{"offset":268,"length":2}},{"content":"fraganela","polygon":[390,547,415,547,415,556,390,556],"confidence":0.738,"span":{"offset":271,"length":9}},{"content":"de","polygon":[417,547,424,547,424,556,417,556],"confidence":0.894,"span":{"offset":281,"length":2}},{"content":"aroma","polygon":[427,547,444,548,444,556,427,556],"confidence":0.623,"span":{"offset":284,"length":5}},{"content":"y","polygon":[446,548,450,548,450,556,445,556],"confidence":0.496,"span":{"offset":290,"length":1}},{"content":"de","polygon":[453,548,461,548,461,556,453,556],"confidence":0.895,"span":{"offset":292,"length":2}},{"content":"genie","polygon":[369,555,382,555,382,564,369,564],"confidence":0.11,"span":{"offset":295,"length":5}},{"content":"ivalala","polygon":[384,555,409,555,409,563,384,564],"confidence":0.237,"span":{"offset":301,"length":7}},{"content":"por","polygon":[411,555,420,555,420,563,411,563],"confidence":0.403,"span":{"offset":309,"length":3}},{"content":"el","polygon":[421,555,427,555,428,563,422,563],"confidence":0.599,"span":{"offset":313,"length":2}},{"content":"Cameli","polygon":[429,555,447,555,448,563,429,563],"confidence":0.553,"span":{"offset":316,"length":6}},{"content":"-","polygon":[449,555,453,555,453,563,449,563],"confidence":0.191,"span":{"offset":323,"length":1}},{"content":"La","polygon":[369,563,376,563,375,572,369,572],"confidence":0.999,"span":{"offset":325,"length":2}},{"content":"fe","polygon":[378,563,386,563,386,572,377,572],"confidence":0.81,"span":{"offset":328,"length":2}},{"content":"y","polygon":[388,563,392,563,391,572,388,572],"confidence":0.841,"span":{"offset":331,"length":1}},{"content":"mura","polygon":[393,563,405,563,405,572,393,572],"confidence":0.47,"span":{"offset":333,"length":4}},{"content":"de","polygon":[407,563,414,563,414,572,407,572],"confidence":0.999,"span":{"offset":338,"length":2}},{"content":"los","polygon":[416,563,424,563,424,572,416,572],"confidence":0.84,"span":{"offset":341,"length":3}},{"content":"tebaore","polygon":[426,563,446,563,446,572,426,572],"confidence":0.227,"span":{"offset":345,"length":7}},{"content":"Tur-","polygon":[448,563,462,563,462,572,448,572],"confidence":0.42,"span":{"offset":353,"length":4}},{"content":"cos","polygon":[368,571,378,571,378,579,368,579],"confidence":0.418,"span":{"offset":358,"length":3}},{"content":"y","polygon":[380,571,384,571,384,579,380,579],"confidence":0.502,"span":{"offset":362,"length":1}},{"content":"Americanos,","polygon":[386,571,418,570,419,579,386,579],"confidence":0.385,"span":{"offset":364,"length":11}},{"content":"forclados","polygon":[420,570,448,570,448,579,420,579],"confidence":0.191,"span":{"offset":376,"length":9}},{"content":"con","polygon":[449,570,461,570,461,578,450,579],"confidence":0.186,"span":{"offset":386,"length":3}},{"content":"Haberactie","polygon":[369,584,400,584,400,592,368,593],"confidence":0.219,"span":{"offset":390,"length":10}},{"content":"det","polygon":[402,584,412,584,411,592,401,592],"confidence":0.73,"span":{"offset":401,"length":3}},{"content":"Conel","polygon":[414,584,430,584,430,592,413,592],"confidence":0.325,"span":{"offset":405,"length":5}},{"content":"&","polygon":[433,584,438,584,437,592,432,592],"confidence":0.047,"span":{"offset":411,"length":1}},{"content":"propor;","polygon":[440,584,463,584,463,593,439,592],"confidence":0.557,"span":{"offset":413,"length":7}},{"content":"cienune","polygon":[368,592,388,591,388,600,368,600],"confidence":0.122,"span":{"offset":421,"length":7}},{"content":"el","polygon":[390,591,396,591,395,600,389,600],"confidence":0.383,"span":{"offset":429,"length":2}},{"content":"gote","polygon":[398,591,409,591,409,600,397,600],"confidence":0.23,"span":{"offset":432,"length":4}},{"content":"min","polygon":[411,591,423,590,423,600,411,600],"confidence":0.551,"span":{"offset":437,"length":3}},{"content":"completo","polygon":[425,590,449,590,448,599,425,600],"confidence":0.329,"span":{"offset":441,"length":8}},{"content":"del","polygon":[451,590,463,589,463,598,450,599],"confidence":0.536,"span":{"offset":450,"length":3}},{"content":"cigarrillo.","polygon":[369,598,397,598,397,607,369,607],"confidence":0.261,"span":{"offset":454,"length":11}},{"content":"Esta","polygon":[275,444,297,444,297,457,275,457],"confidence":0.993,"span":{"offset":466,"length":4}},{"content":"edad","polygon":[301,444,327,444,327,456,301,457],"confidence":0.974,"span":{"offset":471,"length":4}},{"content":"moderna","polygon":[265,461,309,460,309,474,265,474],"confidence":0.86,"span":{"offset":476,"length":7}},{"content":"sabe","polygon":[312,460,339,459,339,473,312,474],"confidence":0.993,"span":{"offset":484,"length":4}},{"content":"escoger","polygon":[251,478,289,477,289,491,252,491],"confidence":0.564,"span":{"offset":489,"length":7}},{"content":"lo","polygon":[292,477,302,477,302,491,292,491],"confidence":0.949,"span":{"offset":497,"length":2}},{"content":"mejor-","polygon":[305,477,348,476,348,489,306,491],"confidence":0.968,"span":{"offset":500,"length":6}},{"content":"por","polygon":[281,495,299,495,299,506,281,507],"confidence":0.997,"span":{"offset":507,"length":3}},{"content":"eso","polygon":[303,495,321,494,321,506,303,506],"confidence":0.777,"span":{"offset":511,"length":3}},{"content":"fuma","polygon":[260,509,287,509,287,523,260,522],"confidence":0.989,"span":{"offset":515,"length":4}},{"content":"cigarrillos","polygon":[291,509,342,507,342,522,290,523],"confidence":0.967,"span":{"offset":520,"length":11}},{"content":"Camel","polygon":[284,524,318,524,319,536,284,537],"confidence":0.993,"span":{"offset":532,"length":5}},{"content":"BHW","polygon":[421,671,440,671,440,681,421,681],"confidence":0.524,"span":{"offset":538,"length":3}},{"content":"50378","polygon":[690,691,694,736,681,738,676,693],"confidence":0.995,"span":{"offset":542,"length":5}},{"content":"1060","polygon":[695,747,698,784,685,784,682,748],"confidence":0.99,"span":{"offset":548,"length":4}}],"lines":[{"content":"36","polygon":[237,136,267,136,267,157,237,158],"spans":[{"offset":0,"length":2}]},{"content":"CHANEL","polygon":[497,453,548,454,547,467,497,465],"spans":[{"offset":3,"length":6}]},{"content":"EL fumadre de ens época es del","polygon":[366,474,460,474,460,484,366,484],"spans":[{"offset":10,"length":30}]},{"content":"mas talgenie que at hi- conocido","polygon":[366,482,460,481,460,489,366,491],"spans":[{"offset":41,"length":32}]},{"content":"B haha de que monne una pri-","polygon":[367,497,461,497,461,506,367,506],"spans":[{"offset":74,"length":28}]},{"content":"ferencla dichlada por el Carol in","polygon":[367,504,461,504,461,512,367,513],"spans":[{"offset":103,"length":33}]},{"content":"prothe evidence de que nie dife-","polygon":[366,512,459,512,459,520,366,520],"spans":[{"offset":137,"length":32}]},{"content":"write ha sido creado para serslicer","polygon":[366,517,461,517,461,526,366,526],"spans":[{"offset":170,"length":35}]},{"content":"La peine más melindresa ne","polygon":[367,534,460,533,460,542,367,543],"spans":[{"offset":206,"length":26}]},{"content":"tradri was mandlo que sesdime","polygon":[367,540,462,540,462,549,367,548],"spans":[{"offset":233,"length":29}]},{"content":"were la fraganela de aroma y de","polygon":[367,547,461,547,461,556,367,556],"spans":[{"offset":263,"length":31}]},{"content":"genie ivalala por el Cameli -","polygon":[369,555,452,554,452,562,369,563],"spans":[{"offset":295,"length":29}]},{"content":"La fe y mura de los tebaore Tur-","polygon":[368,562,461,562,461,571,368,572],"spans":[{"offset":325,"length":32}]},{"content":"cos y Americanos, forclados con","polygon":[368,570,461,569,461,578,368,579],"spans":[{"offset":358,"length":31}]},{"content":"Haberactie det Conel & propor;","polygon":[368,583,462,583,462,592,368,592],"spans":[{"offset":390,"length":30}]},{"content":"cienune el gote min completo del","polygon":[367,591,462,589,462,598,367,600],"spans":[{"offset":421,"length":32}]},{"content":"cigarrillo.","polygon":[368,598,396,598,396,606,368,606],"spans":[{"offset":454,"length":11}]},{"content":"Esta edad","polygon":[274,443,326,443,326,456,274,456],"spans":[{"offset":466,"length":9}]},{"content":"moderna sabe","polygon":[264,461,338,459,338,472,264,474],"spans":[{"offset":476,"length":12}]},{"content":"escoger lo mejor-","polygon":[251,477,347,476,348,489,251,491],"spans":[{"offset":489,"length":17}]},{"content":"por eso","polygon":[280,495,320,494,320,505,280,507],"spans":[{"offset":507,"length":7}]},{"content":"fuma cigarrillos","polygon":[260,508,341,507,341,521,260,522],"spans":[{"offset":515,"length":16}]},{"content":"Camel","polygon":[284,524,318,524,318,536,284,537],"spans":[{"offset":532,"length":5}]},{"content":"BHW","polygon":[420,671,440,671,440,681,419,681],"spans":[{"offset":538,"length":3}]},{"content":"50378 1060","polygon":[689,691,698,783,684,784,676,692],"spans":[{"offset":542,"length":10}]}],"spans":[{"offset":0,"length":552}]}],"tables":[],"paragraphs":[{"spans":[{"offset":0,"length":2}],"boundingRegions":[{"pageNumber":1,"polygon":[237,136,267,136,267,158,237,158]}],"role":"pageNumber","content":"36"},{"spans":[{"offset":3,"length":6}],"boundingRegions":[{"pageNumber":1,"polygon":[497,453,548,454,548,467,497,466]}],"content":"CHANEL"},{"spans":[{"offset":10,"length":195}],"boundingRegions":[{"pageNumber":1,"polygon":[366,474,461,474,461,526,366,526]}],"content":"EL fumadre de ens época es del mas talgenie que at hi- conocido B haha de que monne una pri- ferencla dichlada por el Carol in prothe evidence de que nie dife- write ha sido creado para serslicer"},{"spans":[{"offset":206,"length":259}],"boundingRegions":[{"pageNumber":1,"polygon":[366,534,462,533,463,605,367,606]}],"content":"La peine más melindresa ne tradri was mandlo que sesdime were la fraganela de aroma y de genie ivalala por el Cameli - La fe y mura de los tebaore Tur- cos y Americanos, forclados con Haberactie det Conel & propor; cienune el gote min completo del cigarrillo."},{"spans":[{"offset":466,"length":71}],"boundingRegions":[{"pageNumber":1,"polygon":[251,443,348,443,348,537,251,537]}],"content":"Esta edad moderna sabe escoger lo mejor- por eso fuma cigarrillos Camel"},{"spans":[{"offset":538,"length":3}],"boundingRegions":[{"pageNumber":1,"polygon":[419,671,440,671,440,681,419,681]}],"content":"BHW"},{"spans":[{"offset":542,"length":10}],"boundingRegions":[{"pageNumber":1,"polygon":[676,692,690,691,698,783,684,784]}],"role":"pageFooter","content":"50378 1060"}],"styles":[{"confidence":0.4,"spans":[{"offset":538,"length":3}],"isHandwritten":true}],"contentFormat":"text","sections":[{"spans":[{"offset":2,"length":0},{"offset":2,"length":539}],"elements":["/figures/0","/figures/1","/figures/2","/paragraphs/2","/paragraphs/3","/figures/3","/paragraphs/4","/figures/4","/paragraphs/5"]}],"figures":[{"id":"","boundingRegions":[{"pageNumber":1,"polygon":[247,242,443,243,441,412,246,411]}],"spans":[{"offset":2,"length":0}]},{"id":"","boundingRegions":[{"pageNumber":1,"polygon":[447,319,584,319,584,402,447,402]}],"spans":[{"offset":2,"length":0}]},{"id":"","boundingRegions":[{"pageNumber":1,"polygon":[489,411,556,411,556,528,489,528]}],"spans":[{"offset":3,"length":6}],"elements":["/paragraphs/1"]},{"id":"","boundingRegions":[{"pageNumber":1,"polygon":[465,544,587,544,587,676,465,676]}],"spans":[{"offset":465,"length":0}]},{"id":"","boundingRegions":[{"pageNumber":1,"polygon":[246,551,360,544,367,662,253,669]}],"spans":[{"offset":537,"length":0}]}]}}