{"status":"succeeded","createdDateTime":"2024-08-14T16:32:05Z","lastUpdatedDateTime":"2024-08-14T16:32:06Z","analyzeResult":{"apiVersion":"2024-02-29-preview","modelId":"prebuilt-layout","stringIndexType":"textElements","content":"2076959185A\nPHILIP MORRIS COMPANIES INC. 120 PARK AVENUE, NEW YORK, NY 10017-5592\nINTER-OFFICE CORRESPONDENCE\nTO: All Employees\nDATE: February 11, 1999 FROM: Geoffrey C. Bible\nSUBJECT: Punitive Damages in the Henley Case\nFirst, let me make very clear that I am absolute in my belief that the jury verdict in San Francisco was wrong.\nSecond, the punitive damage award of $50 million is outrageous. Right-minded people inside and outside our company will find it apparent that this jury could not separate fact and logic from prejudice and emotion.\nWe will mount a vigorous appeal and both the punitive damages award and the compensatory damage award should be reversed.\nI regret that our employees must once again cope with a difficult situation. You have shown your mettle in the past and I have no doubt you will do so this time as well.\nBut make no mistake about it. We will do everything in our power to reverse the verdict and the punitive damage award. Our day-to-day work will go forward without interruption or pause. Let me assure you we are already marshaling our forces in preparation for the appeal.","pages":[{"pageNumber":1,"angle":0,"width":754,"height":1000,"unit":"pixel","words":[{"content":"2076959185A","polygon":[715,108,714,216,698,215,697,108],"confidence":0.995,"span":{"offset":0,"length":11}},{"content":"PHILIP","polygon":[54,155,109,155,109,173,54,173],"confidence":0.993,"span":{"offset":12,"length":6}},{"content":"MORRIS","polygon":[113,155,177,155,177,173,113,173],"confidence":0.993,"span":{"offset":19,"length":6}},{"content":"COMPANIES","polygon":[181,155,273,155,273,173,180,173],"confidence":0.828,"span":{"offset":26,"length":9}},{"content":"INC.","polygon":[277,155,312,155,312,173,277,173],"confidence":0.98,"span":{"offset":36,"length":4}},{"content":"120","polygon":[55,173,80,173,80,190,55,190],"confidence":0.998,"span":{"offset":41,"length":3}},{"content":"PARK","polygon":[83,173,120,173,120,190,83,190],"confidence":0.993,"span":{"offset":45,"length":4}},{"content":"AVENUE,","polygon":[126,172,192,172,192,190,126,190],"confidence":0.993,"span":{"offset":50,"length":7}},{"content":"NEW","polygon":[196,172,226,172,226,190,196,190],"confidence":0.999,"span":{"offset":58,"length":3}},{"content":"YORK,","polygon":[234,172,280,172,280,190,234,190],"confidence":0.993,"span":{"offset":62,"length":5}},{"content":"NY","polygon":[283,172,306,172,305,190,283,190],"confidence":0.994,"span":{"offset":68,"length":2}},{"content":"10017-5592","polygon":[310,172,385,172,385,190,309,190],"confidence":0.994,"span":{"offset":71,"length":10}},{"content":"INTER-OFFICE","polygon":[392,156,498,155,498,173,392,172],"confidence":0.982,"span":{"offset":82,"length":12}},{"content":"CORRESPONDENCE","polygon":[504,155,648,155,648,172,504,173],"confidence":0.993,"span":{"offset":95,"length":14}},{"content":"TO:","polygon":[54,202,82,202,82,221,53,220],"confidence":0.993,"span":{"offset":110,"length":3}},{"content":"All","polygon":[97,203,118,203,118,221,97,221],"confidence":0.969,"span":{"offset":114,"length":3}},{"content":"Employees","polygon":[122,203,202,204,201,221,121,221],"confidence":0.995,"span":{"offset":118,"length":9}},{"content":"DATE:","polygon":[372,203,422,203,422,220,372,220],"confidence":0.982,"span":{"offset":128,"length":5}},{"content":"February","polygon":[437,203,497,203,497,220,437,220],"confidence":0.993,"span":{"offset":134,"length":8}},{"content":"11,","polygon":[502,203,520,203,520,220,501,220],"confidence":0.995,"span":{"offset":143,"length":3}},{"content":"1999","polygon":[525,203,557,203,556,220,524,220],"confidence":0.99,"span":{"offset":147,"length":4}},{"content":"FROM:","polygon":[54,233,107,233,106,250,54,250],"confidence":0.995,"span":{"offset":152,"length":5}},{"content":"Geoffrey","polygon":[118,233,172,233,172,251,118,250],"confidence":0.995,"span":{"offset":158,"length":8}},{"content":"C.","polygon":[176,233,189,233,189,251,175,251],"confidence":0.996,"span":{"offset":167,"length":2}},{"content":"Bible","polygon":[193,233,229,233,229,251,192,251],"confidence":0.995,"span":{"offset":170,"length":5}},{"content":"SUBJECT:","polygon":[54,262,132,262,131,280,54,281],"confidence":0.993,"span":{"offset":176,"length":8}},{"content":"Punitive","polygon":[139,262,199,262,199,280,138,280],"confidence":0.993,"span":{"offset":185,"length":8}},{"content":"Damages","polygon":[203,262,268,262,268,280,202,280],"confidence":0.995,"span":{"offset":194,"length":7}},{"content":"in","polygon":[271,262,286,263,286,280,271,280],"confidence":0.996,"span":{"offset":202,"length":2}},{"content":"the","polygon":[291,263,314,263,313,280,291,280],"confidence":0.999,"span":{"offset":205,"length":3}},{"content":"Henley","polygon":[317,263,369,263,369,280,317,280],"confidence":0.993,"span":{"offset":209,"length":6}},{"content":"Case","polygon":[372,263,410,263,410,280,372,280],"confidence":0.993,"span":{"offset":216,"length":4}},{"content":"First,","polygon":[94,307,132,307,132,323,94,323],"confidence":0.994,"span":{"offset":221,"length":6}},{"content":"let","polygon":[136,307,153,306,153,323,136,323],"confidence":0.996,"span":{"offset":228,"length":3}},{"content":"me","polygon":[157,306,176,306,175,323,156,323],"confidence":0.997,"span":{"offset":232,"length":2}},{"content":"make","polygon":[179,306,213,306,213,323,179,323],"confidence":0.992,"span":{"offset":235,"length":4}},{"content":"very","polygon":[217,306,246,306,246,324,216,323],"confidence":0.993,"span":{"offset":240,"length":4}},{"content":"clear","polygon":[249,306,279,306,279,324,249,324],"confidence":0.995,"span":{"offset":245,"length":5}},{"content":"that","polygon":[283,306,312,306,312,324,283,324],"confidence":0.993,"span":{"offset":251,"length":4}},{"content":"I","polygon":[315,306,321,306,321,324,315,324],"confidence":0.996,"span":{"offset":256,"length":1}},{"content":"am","polygon":[325,306,344,306,344,324,324,324],"confidence":0.996,"span":{"offset":258,"length":2}},{"content":"absolute","polygon":[348,306,402,306,402,324,348,324],"confidence":0.993,"span":{"offset":261,"length":8}},{"content":"in","polygon":[405,306,419,306,419,324,405,324],"confidence":0.996,"span":{"offset":270,"length":2}},{"content":"my","polygon":[422,306,441,306,441,324,422,324],"confidence":0.997,"span":{"offset":273,"length":2}},{"content":"belief","polygon":[444,306,480,306,479,324,444,324],"confidence":0.994,"span":{"offset":276,"length":6}},{"content":"that","polygon":[483,306,511,306,511,324,483,324],"confidence":0.993,"span":{"offset":283,"length":4}},{"content":"the","polygon":[514,306,533,306,533,324,514,324],"confidence":0.999,"span":{"offset":288,"length":3}},{"content":"jury","polygon":[537,306,564,306,564,323,537,324],"confidence":0.993,"span":{"offset":292,"length":4}},{"content":"verdict","polygon":[568,306,611,306,611,323,568,323],"confidence":0.993,"span":{"offset":297,"length":7}},{"content":"in","polygon":[614,306,631,306,631,323,614,323],"confidence":0.996,"span":{"offset":305,"length":2}},{"content":"San","polygon":[96,323,121,323,121,340,95,340],"confidence":0.995,"span":{"offset":308,"length":3}},{"content":"Francisco","polygon":[126,323,187,324,187,340,125,340],"confidence":0.995,"span":{"offset":312,"length":9}},{"content":"was","polygon":[191,324,216,325,216,340,190,340],"confidence":0.999,"span":{"offset":322,"length":3}},{"content":"wrong.","polygon":[219,325,263,325,263,340,219,340],"confidence":0.995,"span":{"offset":326,"length":6}},{"content":"Second,","polygon":[95,352,146,352,146,370,95,370],"confidence":0.993,"span":{"offset":333,"length":7}},{"content":"the","polygon":[150,352,169,352,169,370,150,370],"confidence":0.996,"span":{"offset":341,"length":3}},{"content":"punitive","polygon":[172,352,226,353,226,370,172,370],"confidence":0.993,"span":{"offset":345,"length":8}},{"content":"damage","polygon":[229,353,281,353,281,370,229,370],"confidence":0.994,"span":{"offset":354,"length":6}},{"content":"award","polygon":[285,353,324,353,324,370,285,370],"confidence":0.995,"span":{"offset":361,"length":5}},{"content":"of","polygon":[327,353,339,353,339,370,327,370],"confidence":0.995,"span":{"offset":367,"length":2}},{"content":"$50","polygon":[342,353,368,353,367,370,342,370],"confidence":0.994,"span":{"offset":370,"length":3}},{"content":"million","polygon":[371,353,415,353,415,370,371,370],"confidence":0.994,"span":{"offset":374,"length":7}},{"content":"is","polygon":[418,353,431,353,431,370,418,370],"confidence":0.996,"span":{"offset":382,"length":2}},{"content":"outrageous.","polygon":[435,353,509,352,509,370,434,370],"confidence":0.99,"span":{"offset":385,"length":11}},{"content":"Right-minded","polygon":[517,352,605,352,605,371,516,370],"confidence":0.99,"span":{"offset":397,"length":12}},{"content":"people","polygon":[608,352,652,352,651,371,608,371],"confidence":0.993,"span":{"offset":410,"length":6}},{"content":"inside","polygon":[96,370,136,370,135,386,95,386],"confidence":0.993,"span":{"offset":417,"length":6}},{"content":"and","polygon":[140,370,164,370,163,386,139,386],"confidence":0.998,"span":{"offset":424,"length":3}},{"content":"outside","polygon":[167,370,214,370,213,387,167,386],"confidence":0.993,"span":{"offset":428,"length":7}},{"content":"our","polygon":[217,370,239,370,239,387,217,387],"confidence":0.998,"span":{"offset":436,"length":3}},{"content":"company","polygon":[243,370,298,370,298,387,242,387],"confidence":0.993,"span":{"offset":440,"length":7}},{"content":"will","polygon":[302,370,327,370,327,387,301,387],"confidence":0.993,"span":{"offset":448,"length":4}},{"content":"find","polygon":[331,370,354,370,354,387,330,387],"confidence":0.993,"span":{"offset":453,"length":4}},{"content":"it","polygon":[357,370,370,370,370,387,357,387],"confidence":0.996,"span":{"offset":458,"length":2}},{"content":"apparent","polygon":[374,370,431,370,430,387,373,387],"confidence":0.994,"span":{"offset":461,"length":8}},{"content":"that","polygon":[434,370,461,370,460,387,434,387],"confidence":0.993,"span":{"offset":470,"length":4}},{"content":"this","polygon":[464,370,489,370,488,387,464,387],"confidence":0.993,"span":{"offset":475,"length":4}},{"content":"jury","polygon":[492,370,520,370,520,387,492,387],"confidence":0.993,"span":{"offset":480,"length":4}},{"content":"could","polygon":[524,370,558,370,558,387,523,387],"confidence":0.995,"span":{"offset":485,"length":5}},{"content":"not","polygon":[562,370,583,370,582,387,561,387],"confidence":0.997,"span":{"offset":491,"length":3}},{"content":"separate","polygon":[586,370,644,370,643,386,586,387],"confidence":0.994,"span":{"offset":495,"length":8}},{"content":"fact","polygon":[95,387,122,387,121,404,95,404],"confidence":0.992,"span":{"offset":504,"length":4}},{"content":"and","polygon":[125,387,149,387,149,404,125,404],"confidence":0.999,"span":{"offset":509,"length":3}},{"content":"logic","polygon":[152,387,180,387,180,404,152,404],"confidence":0.993,"span":{"offset":513,"length":5}},{"content":"from","polygon":[183,387,215,387,215,404,183,404],"confidence":0.993,"span":{"offset":519,"length":4}},{"content":"prejudice","polygon":[219,387,278,387,278,404,218,404],"confidence":0.993,"span":{"offset":524,"length":9}},{"content":"and","polygon":[281,387,306,387,306,404,281,404],"confidence":0.995,"span":{"offset":534,"length":3}},{"content":"emotion.","polygon":[309,387,366,387,366,403,309,404],"confidence":0.989,"span":{"offset":538,"length":8}},{"content":"We","polygon":[96,416,118,416,118,433,96,433],"confidence":0.996,"span":{"offset":547,"length":2}},{"content":"will","polygon":[121,416,146,416,145,433,121,433],"confidence":0.993,"span":{"offset":550,"length":4}},{"content":"mount","polygon":[149,416,191,416,190,433,149,433],"confidence":0.996,"span":{"offset":555,"length":5}},{"content":"a","polygon":[195,416,202,416,202,433,194,433],"confidence":0.996,"span":{"offset":561,"length":1}},{"content":"vigorous","polygon":[205,416,260,416,260,433,205,433],"confidence":0.994,"span":{"offset":563,"length":8}},{"content":"appeal","polygon":[264,416,306,416,306,433,263,433],"confidence":0.989,"span":{"offset":572,"length":6}},{"content":"and","polygon":[310,416,333,416,332,433,310,433],"confidence":0.999,"span":{"offset":579,"length":3}},{"content":"both","polygon":[336,416,364,416,364,433,336,433],"confidence":0.993,"span":{"offset":583,"length":4}},{"content":"the","polygon":[369,416,391,416,390,433,369,433],"confidence":0.999,"span":{"offset":588,"length":3}},{"content":"punitive","polygon":[394,416,448,416,447,433,394,433],"confidence":0.993,"span":{"offset":592,"length":8}},{"content":"damages","polygon":[452,416,507,416,507,433,451,433],"confidence":0.993,"span":{"offset":601,"length":7}},{"content":"award","polygon":[515,416,555,416,555,432,515,433],"confidence":0.97,"span":{"offset":609,"length":5}},{"content":"and","polygon":[559,416,584,416,583,432,559,432],"confidence":0.999,"span":{"offset":615,"length":3}},{"content":"the","polygon":[587,416,610,416,610,432,586,432],"confidence":0.999,"span":{"offset":619,"length":3}},{"content":"compensatory","polygon":[96,435,186,433,186,450,96,450],"confidence":0.993,"span":{"offset":623,"length":12}},{"content":"damage","polygon":[189,433,239,433,239,450,189,450],"confidence":0.996,"span":{"offset":636,"length":6}},{"content":"award","polygon":[243,433,283,433,283,450,243,450],"confidence":0.996,"span":{"offset":643,"length":5}},{"content":"should","polygon":[287,433,329,433,329,449,287,450],"confidence":0.996,"span":{"offset":649,"length":6}},{"content":"be","polygon":[332,433,347,433,347,449,332,449],"confidence":0.996,"span":{"offset":656,"length":2}},{"content":"reversed.","polygon":[350,433,411,433,411,449,350,449],"confidence":0.993,"span":{"offset":659,"length":9}},{"content":"I","polygon":[95,463,101,463,101,480,95,480],"confidence":0.996,"span":{"offset":669,"length":1}},{"content":"regret","polygon":[104,463,146,463,145,480,104,480],"confidence":0.993,"span":{"offset":671,"length":6}},{"content":"that","polygon":[149,463,176,463,176,480,149,480],"confidence":0.993,"span":{"offset":678,"length":4}},{"content":"our","polygon":[180,463,201,463,201,480,179,480],"confidence":0.998,"span":{"offset":683,"length":3}},{"content":"employees","polygon":[204,463,271,462,271,480,204,480],"confidence":0.994,"span":{"offset":687,"length":9}},{"content":"must","polygon":[274,462,307,462,307,480,274,480],"confidence":0.993,"span":{"offset":697,"length":4}},{"content":"once","polygon":[311,462,339,462,339,480,311,480],"confidence":0.993,"span":{"offset":702,"length":4}},{"content":"again","polygon":[343,462,377,462,377,480,343,480],"confidence":0.994,"span":{"offset":707,"length":5}},{"content":"cope","polygon":[381,462,410,462,410,480,380,480],"confidence":0.993,"span":{"offset":713,"length":4}},{"content":"with","polygon":[414,462,443,462,443,480,413,480],"confidence":0.993,"span":{"offset":718,"length":4}},{"content":"a","polygon":[446,462,454,462,454,480,446,480],"confidence":0.995,"span":{"offset":723,"length":1}},{"content":"difficult","polygon":[458,462,508,462,508,479,457,480],"confidence":0.993,"span":{"offset":725,"length":9}},{"content":"situation.","polygon":[512,462,576,462,576,479,511,479],"confidence":0.993,"span":{"offset":735,"length":10}},{"content":"You","polygon":[580,462,604,462,604,479,580,479],"confidence":0.999,"span":{"offset":746,"length":3}},{"content":"have","polygon":[607,462,642,462,642,479,607,479],"confidence":0.993,"span":{"offset":750,"length":4}},{"content":"shown","polygon":[95,481,138,480,138,497,95,497],"confidence":0.996,"span":{"offset":755,"length":5}},{"content":"your","polygon":[142,480,171,480,171,497,141,497],"confidence":0.993,"span":{"offset":761,"length":4}},{"content":"mettle","polygon":[175,480,213,480,213,497,174,497],"confidence":0.994,"span":{"offset":766,"length":6}},{"content":"in","polygon":[217,480,230,480,230,497,216,497],"confidence":0.99,"span":{"offset":773,"length":2}},{"content":"the","polygon":[234,480,257,480,257,497,234,497],"confidence":0.988,"span":{"offset":776,"length":3}},{"content":"past","polygon":[260,480,288,480,288,497,260,497],"confidence":0.993,"span":{"offset":780,"length":4}},{"content":"and","polygon":[292,480,316,480,316,497,291,497],"confidence":0.999,"span":{"offset":785,"length":3}},{"content":"I","polygon":[319,480,325,480,324,497,319,497],"confidence":0.996,"span":{"offset":789,"length":1}},{"content":"have","polygon":[328,480,359,480,359,497,328,497],"confidence":0.993,"span":{"offset":791,"length":4}},{"content":"no","polygon":[363,480,379,480,378,497,362,497],"confidence":0.995,"span":{"offset":796,"length":2}},{"content":"doubt","polygon":[382,480,419,480,419,497,382,497],"confidence":0.996,"span":{"offset":799,"length":5}},{"content":"you","polygon":[422,480,445,480,445,497,422,497],"confidence":0.999,"span":{"offset":805,"length":3}},{"content":"will","polygon":[449,480,473,480,472,497,448,497],"confidence":0.993,"span":{"offset":809,"length":4}},{"content":"do","polygon":[477,480,491,480,491,496,476,497],"confidence":0.996,"span":{"offset":814,"length":2}},{"content":"so","polygon":[496,480,508,480,508,496,495,496],"confidence":0.996,"span":{"offset":817,"length":2}},{"content":"this","polygon":[512,480,537,480,536,496,511,496],"confidence":0.992,"span":{"offset":820,"length":4}},{"content":"time","polygon":[540,480,569,480,569,496,540,496],"confidence":0.993,"span":{"offset":825,"length":4}},{"content":"as","polygon":[573,480,587,480,587,496,573,496],"confidence":0.997,"span":{"offset":830,"length":2}},{"content":"well.","polygon":[591,480,622,480,622,495,590,496],"confidence":0.995,"span":{"offset":833,"length":5}},{"content":"But","polygon":[96,510,119,510,119,526,96,526],"confidence":0.999,"span":{"offset":839,"length":3}},{"content":"make","polygon":[122,510,158,510,158,526,122,526],"confidence":0.993,"span":{"offset":843,"length":4}},{"content":"no","polygon":[162,510,177,509,177,527,162,527],"confidence":0.996,"span":{"offset":848,"length":2}},{"content":"mistake","polygon":[181,509,233,509,233,527,181,527],"confidence":0.995,"span":{"offset":851,"length":7}},{"content":"about","polygon":[237,509,271,509,271,527,237,527],"confidence":0.998,"span":{"offset":859,"length":5}},{"content":"it.","polygon":[274,509,290,509,290,527,274,527],"confidence":0.995,"span":{"offset":865,"length":3}},{"content":"We","polygon":[298,509,318,509,318,527,298,527],"confidence":0.997,"span":{"offset":869,"length":2}},{"content":"will","polygon":[321,509,346,509,346,527,321,527],"confidence":0.994,"span":{"offset":872,"length":4}},{"content":"do","polygon":[349,509,365,509,365,527,349,527],"confidence":0.994,"span":{"offset":877,"length":2}},{"content":"everything","polygon":[368,509,436,509,436,527,368,527],"confidence":0.993,"span":{"offset":880,"length":10}},{"content":"in","polygon":[439,509,454,509,454,527,439,527],"confidence":0.998,"span":{"offset":891,"length":2}},{"content":"our","polygon":[457,509,479,509,479,527,457,527],"confidence":0.999,"span":{"offset":894,"length":3}},{"content":"power","polygon":[482,509,521,509,521,526,482,527],"confidence":0.995,"span":{"offset":898,"length":5}},{"content":"to","polygon":[525,509,537,509,537,526,525,526],"confidence":0.996,"span":{"offset":904,"length":2}},{"content":"reverse","polygon":[541,510,588,510,588,525,541,526],"confidence":0.995,"span":{"offset":907,"length":7}},{"content":"the","polygon":[591,510,614,510,614,525,591,525],"confidence":0.994,"span":{"offset":915,"length":3}},{"content":"verdict","polygon":[96,527,140,527,140,544,95,543],"confidence":0.995,"span":{"offset":919,"length":7}},{"content":"and","polygon":[144,527,169,527,168,544,143,544],"confidence":0.999,"span":{"offset":927,"length":3}},{"content":"the","polygon":[173,527,192,527,191,544,172,544],"confidence":0.999,"span":{"offset":931,"length":3}},{"content":"punitive","polygon":[195,526,251,526,250,544,195,544],"confidence":0.995,"span":{"offset":935,"length":8}},{"content":"damage","polygon":[254,526,304,526,304,544,254,544],"confidence":0.996,"span":{"offset":944,"length":6}},{"content":"award.","polygon":[308,526,352,526,351,544,308,544],"confidence":0.996,"span":{"offset":951,"length":6}},{"content":"Our","polygon":[360,526,384,526,384,544,359,544],"confidence":0.999,"span":{"offset":958,"length":3}},{"content":"day-to-day","polygon":[388,526,456,526,456,544,387,544],"confidence":0.993,"span":{"offset":962,"length":10}},{"content":"work","polygon":[460,526,492,526,492,544,459,544],"confidence":0.993,"span":{"offset":973,"length":4}},{"content":"will","polygon":[496,526,519,526,519,544,495,544],"confidence":0.994,"span":{"offset":978,"length":4}},{"content":"go","polygon":[523,526,537,526,537,543,522,543],"confidence":0.995,"span":{"offset":983,"length":2}},{"content":"forward","polygon":[541,526,591,526,591,543,540,543],"confidence":0.994,"span":{"offset":986,"length":7}},{"content":"without","polygon":[596,526,648,526,648,542,595,543],"confidence":0.995,"span":{"offset":994,"length":7}},{"content":"interruption","polygon":[95,544,175,544,175,561,96,561],"confidence":0.993,"span":{"offset":1002,"length":12}},{"content":"or","polygon":[179,544,191,544,191,561,179,561],"confidence":0.996,"span":{"offset":1015,"length":2}},{"content":"pause.","polygon":[194,544,237,544,237,561,194,561],"confidence":0.994,"span":{"offset":1018,"length":6}},{"content":"Let","polygon":[244,544,265,544,265,561,245,561],"confidence":0.999,"span":{"offset":1025,"length":3}},{"content":"me","polygon":[268,544,289,544,289,561,268,561],"confidence":0.997,"span":{"offset":1029,"length":2}},{"content":"assure","polygon":[293,544,334,544,334,561,293,561],"confidence":0.993,"span":{"offset":1032,"length":6}},{"content":"you","polygon":[338,544,362,544,362,561,338,561],"confidence":0.995,"span":{"offset":1039,"length":3}},{"content":"we","polygon":[365,544,383,544,383,561,365,561],"confidence":0.996,"span":{"offset":1043,"length":2}},{"content":"are","polygon":[387,544,407,543,407,561,387,561],"confidence":0.998,"span":{"offset":1046,"length":3}},{"content":"already","polygon":[411,543,458,543,458,561,411,561],"confidence":0.993,"span":{"offset":1050,"length":7}},{"content":"marshaling","polygon":[461,543,536,543,536,560,461,561],"confidence":0.993,"span":{"offset":1058,"length":10}},{"content":"our","polygon":[540,543,561,543,561,560,539,560],"confidence":0.997,"span":{"offset":1069,"length":3}},{"content":"forces","polygon":[565,543,602,543,602,560,564,560],"confidence":0.993,"span":{"offset":1073,"length":6}},{"content":"in","polygon":[606,543,621,543,620,560,605,560],"confidence":0.996,"span":{"offset":1080,"length":2}},{"content":"preparation","polygon":[95,562,172,561,172,578,95,578],"confidence":0.993,"span":{"offset":1083,"length":11}},{"content":"for","polygon":[176,561,194,561,194,578,176,578],"confidence":0.996,"span":{"offset":1095,"length":3}},{"content":"the","polygon":[198,561,218,560,218,578,197,578],"confidence":0.999,"span":{"offset":1099,"length":3}},{"content":"appeal.","polygon":[222,560,272,560,272,578,222,578],"confidence":0.987,"span":{"offset":1103,"length":7}}],"lines":[{"content":"2076959185A","polygon":[715,107,715,215,697,215,697,107],"spans":[{"offset":0,"length":11}]},{"content":"PHILIP MORRIS COMPANIES INC.","polygon":[54,155,311,155,311,172,54,172],"spans":[{"offset":12,"length":28}]},{"content":"120 PARK AVENUE, NEW YORK, NY 10017-5592","polygon":[55,172,384,172,384,189,55,189],"spans":[{"offset":41,"length":40}]},{"content":"INTER-OFFICE CORRESPONDENCE","polygon":[391,155,647,155,647,172,391,172],"spans":[{"offset":82,"length":27}]},{"content":"TO: All Employees","polygon":[53,202,201,203,200,221,53,220],"spans":[{"offset":110,"length":17}]},{"content":"DATE: February 11, 1999","polygon":[371,202,556,202,556,219,371,219],"spans":[{"offset":128,"length":23}]},{"content":"FROM: Geoffrey C. Bible","polygon":[54,232,228,232,228,250,54,250],"spans":[{"offset":152,"length":23}]},{"content":"SUBJECT: Punitive Damages in the Henley Case","polygon":[54,262,409,262,409,280,54,280],"spans":[{"offset":176,"length":44}]},{"content":"First, let me make very clear that I am absolute in my belief that the jury verdict in","polygon":[93,305,630,305,630,323,93,323],"spans":[{"offset":221,"length":86}]},{"content":"San Francisco was wrong.","polygon":[95,322,262,324,262,340,95,339],"spans":[{"offset":308,"length":24}]},{"content":"Second, the punitive damage award of $50 million is outrageous. Right-minded people","polygon":[95,352,651,352,651,370,95,370],"spans":[{"offset":333,"length":83}]},{"content":"inside and outside our company will find it apparent that this jury could not separate","polygon":[95,369,643,369,643,387,95,386],"spans":[{"offset":417,"length":86}]},{"content":"fact and logic from prejudice and emotion.","polygon":[94,386,365,386,365,403,94,403],"spans":[{"offset":504,"length":42}]},{"content":"We will mount a vigorous appeal and both the punitive damages award and the","polygon":[95,415,609,415,609,432,95,433],"spans":[{"offset":547,"length":75}]},{"content":"compensatory damage award should be reversed.","polygon":[95,433,410,432,410,448,95,450],"spans":[{"offset":623,"length":45}]},{"content":"I regret that our employees must once again cope with a difficult situation. You have","polygon":[95,462,641,462,641,479,95,480],"spans":[{"offset":669,"length":85}]},{"content":"shown your mettle in the past and I have no doubt you will do so this time as well.","polygon":[94,480,621,479,621,496,94,497],"spans":[{"offset":755,"length":83}]},{"content":"But make no mistake about it. We will do everything in our power to reverse the","polygon":[95,509,613,508,613,526,95,527],"spans":[{"offset":839,"length":79}]},{"content":"verdict and the punitive damage award. Our day-to-day work will go forward without","polygon":[95,526,647,525,647,543,95,544],"spans":[{"offset":919,"length":82}]},{"content":"interruption or pause. Let me assure you we are already marshaling our forces in","polygon":[95,543,620,542,620,560,95,561],"spans":[{"offset":1002,"length":80}]},{"content":"preparation for the appeal.","polygon":[95,561,271,560,271,577,95,578],"spans":[{"offset":1083,"length":27}]}],"spans":[{"offset":0,"length":1110}]}],"tables":[],"paragraphs":[{"spans":[{"offset":0,"length":11}],"boundingRegions":[{"pageNumber":1,"polygon":[697,107,715,107,715,215,697,215]}],"content":"2076959185A"},{"spans":[{"offset":12,"length":69}],"boundingRegions":[{"pageNumber":1,"polygon":[54,155,384,155,384,189,54,189]}],"content":"PHILIP MORRIS COMPANIES INC. 120 PARK AVENUE, NEW YORK, NY 10017-5592"},{"spans":[{"offset":82,"length":27}],"boundingRegions":[{"pageNumber":1,"polygon":[391,155,647,155,647,172,391,172]}],"role":"pageHeader","content":"INTER-OFFICE CORRESPONDENCE"},{"spans":[{"offset":110,"length":17}],"boundingRegions":[{"pageNumber":1,"polygon":[53,202,201,203,201,221,53,220]}],"content":"TO: All Employees"},{"spans":[{"offset":128,"length":47}],"boundingRegions":[{"pageNumber":1,"polygon":[554,185,558,219,56,266,52,232]}],"content":"DATE: February 11, 1999 FROM: Geoffrey C. Bible"},{"spans":[{"offset":176,"length":44}],"boundingRegions":[{"pageNumber":1,"polygon":[54,262,409,262,409,280,54,280]}],"content":"SUBJECT: Punitive Damages in the Henley Case"},{"spans":[{"offset":221,"length":111}],"boundingRegions":[{"pageNumber":1,"polygon":[93,305,630,305,630,340,93,340]}],"content":"First, let me make very clear that I am absolute in my belief that the jury verdict in San Francisco was wrong."},{"spans":[{"offset":333,"length":213}],"boundingRegions":[{"pageNumber":1,"polygon":[94,352,651,352,651,403,94,403]}],"content":"Second, the punitive damage award of $50 million is outrageous. Right-minded people inside and outside our company will find it apparent that this jury could not separate fact and logic from prejudice and emotion."},{"spans":[{"offset":547,"length":121}],"boundingRegions":[{"pageNumber":1,"polygon":[95,415,609,415,609,450,95,450]}],"content":"We will mount a vigorous appeal and both the punitive damages award and the compensatory damage award should be reversed."},{"spans":[{"offset":669,"length":169}],"boundingRegions":[{"pageNumber":1,"polygon":[94,462,641,462,641,497,94,497]}],"content":"I regret that our employees must once again cope with a difficult situation. You have shown your mettle in the past and I have no doubt you will do so this time as well."},{"spans":[{"offset":839,"length":271}],"boundingRegions":[{"pageNumber":1,"polygon":[95,509,647,508,647,577,95,578]}],"content":"But make no mistake about it. We will do everything in our power to reverse the verdict and the punitive damage award. Our day-to-day work will go forward without interruption or pause. Let me assure you we are already marshaling our forces in preparation for the appeal."}],"styles":[],"contentFormat":"text","sections":[{"spans":[{"offset":0,"length":81},{"offset":110,"length":1000}],"elements":["/paragraphs/0","/paragraphs/1","/paragraphs/3","/paragraphs/4","/paragraphs/5","/paragraphs/6","/paragraphs/7","/paragraphs/8","/paragraphs/9","/paragraphs/10"]}]}}